csv_exporter/__init__.py
csv_exporter/exporter.py
django_csv_exporter-1.2.dist-info/DESCRIPTION.rst
django_csv_exporter-1.2.dist-info/METADATA
django_csv_exporter-1.2.dist-info/RECORD
django_csv_exporter-1.2.dist-info/WHEEL
django_csv_exporter-1.2.dist-info/metadata.json
django_csv_exporter-1.2.dist-info/top_level.txt
