Metadata-Version: 2.0
Name: django-csv-exporter
Version: 1.2
Summary: A django package to export data in a csv with File export.
Home-page: https://github.com/istrategylabs/django-csv-exporter
Author: Joseph Solomon
Author-email: josephs@isl.co
License: MIT
Keywords: django csv file image zip
Platform: UNKNOWN
Classifier: Topic :: Utilities
Classifier: License :: OSI Approved :: MIT License
